helper_decorators/__init__.py
helper_decorators/timing.py
helper_decorators-0.1.4.dist-info/LICENSE
helper_decorators-0.1.4.dist-info/METADATA
helper_decorators-0.1.4.dist-info/WHEEL
helper_decorators-0.1.4.dist-info/top_level.txt
helper_decorators-0.1.4.dist-info/RECORD
