Metadata-Version: 2.1
Name: helper_decorators
Version: 0.1.4
Summary: Python decorator functions for regular use.
Home-page: https://github.com/kavinda-kobbekaduwe/helper_decorators
Author: Kavinda Kobbekaduwe
Author-email: kavindakobbekaduwe@gmail.com
Classifier: Programming Language :: Python :: 3
Classifier: License :: OSI Approved :: MIT License
Classifier: Operating System :: OS Independent
Requires-Python: >=3.6
License-File: LICENSE
